smartrappy/__init__.py
smartrappy/__main__.py
smartrappy/analyser.py
smartrappy/models.py
smartrappy/notebook_parser.py
smartrappy/qmd_parser.py
smartrappy/reporters.py
smartrappy-0.0.9.dist-info/licenses/LICENSE
smartrappy-0.0.9.dist-info/METADATA
smartrappy-0.0.9.dist-info/WHEEL
smartrappy-0.0.9.dist-info/entry_points.txt
smartrappy-0.0.9.dist-info/top_level.txt
smartrappy-0.0.9.dist-info/RECORD
