Metadata-Version: 2.4
Name: smartrappy
Version: 0.0.9
Summary: Smart reproducible analytical pipeline visualisation.
Author-email: Arthur Turrell <anon@anon.gmail.com>
License-Expression: MIT
Classifier: Development Status :: 4 - Beta
Classifier: Programming Language :: Python :: 3.10
Classifier: Programming Language :: Python :: 3.11
Classifier: Programming Language :: Python :: 3.12
Classifier: Programming Language :: Python :: 3.13
Requires-Python: >=3.10
License-File: LICENSE
Requires-Dist: click>=8.1.8
Requires-Dist: graphviz>=0.20.3
Requires-Dist: matplotlib>=3.10.0
Requires-Dist: pandas>=2.2.3
Requires-Dist: rich>=13.9.4
Dynamic: license-file
